newstldr/__init__.py
newstldr/__models__.py
newstldr/__views__.py
newstldr/article_parser.py
newstldr/cli.py
newstldr/core.py
newstldr/imagesize.py
newstldr/youtube.py
newstldr-0.2.0.dist-info/METADATA
newstldr-0.2.0.dist-info/RECORD
newstldr-0.2.0.dist-info/WHEEL
newstldr-0.2.0.dist-info/top_level.txt
